simple_console_menu/Menu.py
simple_console_menu/Menu_old.py
simple_console_menu/__init__.py
simple_console_menu-1.0.4.dist-info/licenses/LICENSE
simple_console_menu-1.0.4.dist-info/METADATA
simple_console_menu-1.0.4.dist-info/WHEEL
simple_console_menu-1.0.4.dist-info/top_level.txt
simple_console_menu-1.0.4.dist-info/RECORD
