Metadata-Version: 2.4
Name: simple-console-menu
Version: 1.0.4
Summary: A simple console menu
Home-page: https://github.com/mikeee1/simple-console-menu
Author: mikeee
Author-email: mikevansmaalen@gmail.com
Project-URL: Bug Tracker, https://github.com/mikeee1/simple-console-menu/issues
Project-URL: Documentation, https://github.com/mikeee1/simple-console-menu/wiki
Classifier: Programming Language :: Python :: 3
Classifier: License :: OSI Approved :: MIT License
Classifier: Operating System :: OS Independent
Requires-Python: >=3.6
License-File: LICENSE
Provides-Extra: test
Requires-Dist: pytest>=6.0; extra == "test"
Requires-Dist: pytest-mock>=3.0; extra == "test"
Dynamic: license-file
